mjvar/__init__.py
mjvar/var.py
mjvar-0.0.1.dist-info/METADATA
mjvar-0.0.1.dist-info/WHEEL
mjvar-0.0.1.dist-info/top_level.txt
mjvar-0.0.1.dist-info/RECORD
