Metadata-Version: 2.1
Name: mjvar
Version: 0.0.1
Summary: 参数化工具
Author: MJ
